{
  "_note1": "KEEP THIS FILE! Check it into a version control system (VCS) like git.",
  "_note2": "ObjectBox manages crucial IDs for your object model. See docs for details.",
  "_note3": "If you have VCS merge conflicts, you must resolve them according to ObjectBox docs.",
  "entities": [
    {
      "id": "1:1565139607905705435",
      "lastPropertyId": "26:1886093547491996978",
      "name": "EpisodeEntity",
      "properties": [
        {
          "id": "1:4670561052217846231",
          "name": "id",
          "type": 6,
          "flags": 1
        },
        {
          "id": "2:2662069751007399050",
          "name": "eId",
          "type": 6
        },
        {
          "id": "3:2894976091804058789",
          "name": "title",
          "type": 9
        },
        {
          "id": "4:4329526841166662602",
          "name": "description",
          "type": 9
        },
        {
          "id": "5:3054363751521067596",
          "name": "guid",
          "type": 9
        },
        {
          "id": "6:1573153674570213847",
          "name": "datePublished",
          "type": 6
        },
        {
          "id": "7:6782909844481842595",
          "name": "datePublishedPretty",
          "type": 9
        },
        {
          "id": "8:7580731945232437536",
          "name": "enclosureUrl",
          "type": 9
        },
        {
          "id": "9:7251155709238231353",
          "name": "enclosureLength",
          "type": 6
        },
        {
          "id": "10:7378168781950407657",
          "name": "duration",
          "type": 6
        },
        {
          "id": "11:4133060487547384495",
          "name": "explicit",
          "type": 6
        },
        {
          "id": "12:502446722681619724",
          "name": "episodeNr",
          "type": 6
        },
        {
          "id": "13:8573786366849211392",
          "name": "episodeType",
          "type": 9
        },
        {
          "id": "14:6785024666013952419",
          "name": "season",
          "type": 6
        },
        {
          "id": "15:5800456178041182279",
          "name": "image",
          "type": 9
        },
        {
          "id": "16:8404203205950663405",
          "name": "link",
          "type": 9
        },
        {
          "id": "17:6856879803896141474",
          "name": "feedUrl",
          "type": 9
        },
        {
          "id": "18:9025815632140074550",
          "name": "feedImage",
          "type": 9
        },
        {
          "id": "19:3974881699213436009",
          "name": "feedId",
          "type": 6
        },
        {
          "id": "20:2148929595363273923",
          "name": "podcastGuid",
          "type": 9
        },
        {
          "id": "21:783674117604261378",
          "name": "favorite",
          "type": 1
        },
        {
          "id": "22:1095060026663765051",
          "name": "read",
          "type": 1
        },
        {
          "id": "23:7541322564005801263",
          "name": "completed",
          "type": 1
        },
        {
          "id": "24:522667113853777195",
          "name": "position",
          "type": 6
        },
        {
          "id": "25:6290802938905714025",
          "name": "filePath",
          "type": 9
        },
        {
          "id": "26:1886093547491996978",
          "name": "podcastId",
          "type": 11,
          "flags": 520,
          "indexId": "1:1126246801486907936",
          "relationTarget": "PodcastEntity"
        }
      ],
      "relations": []
    },
    {
      "id": "2:6590084371707452549",
      "lastPropertyId": "18:945864541081495901",
      "name": "PodcastEntity",
      "properties": [
        {
          "id": "1:5979486489309103380",
          "name": "id",
          "type": 6,
          "flags": 1
        },
        {
          "id": "2:4325799128129907292",
          "name": "pId",
          "type": 6
        },
        {
          "id": "3:704359096505156456",
          "name": "podcastGuid",
          "type": 9
        },
        {
          "id": "4:3305081657196920305",
          "name": "title",
          "type": 9
        },
        {
          "id": "5:1099235061316896203",
          "name": "url",
          "type": 9
        },
        {
          "id": "6:7805721346745967317",
          "name": "link",
          "type": 9
        },
        {
          "id": "7:6792149331943271003",
          "name": "description",
          "type": 9
        },
        {
          "id": "8:1341617678989576884",
          "name": "author",
          "type": 9
        },
        {
          "id": "9:5460988606514859371",
          "name": "ownerName",
          "type": 9
        },
        {
          "id": "10:4043638115481313914",
          "name": "artwork",
          "type": 9
        },
        {
          "id": "11:1511026048992656246",
          "name": "lastUpdateTime",
          "type": 6
        },
        {
          "id": "12:5702708520446065096",
          "name": "language",
          "type": 9
        },
        {
          "id": "13:4974944475010125855",
          "name": "explicit",
          "type": 1
        },
        {
          "id": "14:394027088125504604",
          "name": "medium",
          "type": 9
        },
        {
          "id": "15:3012060787921803881",
          "name": "episodeCount",
          "type": 6
        },
        {
          "id": "16:5983946716952113249",
          "name": "categories",
          "type": 30
        },
        {
          "id": "17:8120025628198903036",
          "name": "subscribed",
          "type": 1
        },
        {
          "id": "18:945864541081495901",
          "name": "artworkBytes",
          "type": 23
        }
      ],
      "relations": []
    }
  ],
  "lastEntityId": "2:6590084371707452549",
  "lastIndexId": "1:1126246801486907936",
  "lastRelationId": "0:0",
  "lastSequenceId": "0:0",
  "modelVersion": 5,
  "modelVersionParserMinimum": 5,
  "retiredEntityUids": [],
  "retiredIndexUids": [],
  "retiredPropertyUids": [],
  "retiredRelationUids": [],
  "version": 1
}